gps_timemachine/__init__.py
gps_timemachine/errors.py
gps_timemachine/gps.py
gps_timemachine/static/__init__.py
gps_timemachine/static/tai-utc.dat
gps_timemachine/test/__init__.py
gps_timemachine/test/test_gps.py
gps_timemachine-1.1.5.dist-info/LICENSE
gps_timemachine-1.1.5.dist-info/METADATA
gps_timemachine-1.1.5.dist-info/WHEEL
gps_timemachine-1.1.5.dist-info/top_level.txt
gps_timemachine-1.1.5.dist-info/RECORD
