Metadata-Version: 2.1
Name: gps-timemachine
Version: 1.1.5
Summary: Adjust GPS datetimes to UTC.
Author-email: NSIDC Development Team <programmers@nsidc.org>
License: This software was developed by the National Snow and Ice Data Center (NSIDC) at
Project-URL: Homepage, https://github.com/nsidc/gps-timemachine
Project-URL: Repository, https://github.com/nsidc/gps-timemachine
Requires-Python: >=3.10
License-File: LICENSE
